extends/__init__.py
extends-0.1.0.dist-info/WHEEL
extends-0.1.0.dist-info/METADATA
extends-0.1.0.dist-info/RECORD
